ai_am/__init__.py
ai_am/hacks/__init__.py
ai_am/hacks/dir_tree.py
ai_am-0.1.0.dist-info/licenses/LICENSE
ai_am-0.1.0.dist-info/METADATA
ai_am-0.1.0.dist-info/WHEEL
ai_am-0.1.0.dist-info/top_level.txt
ai_am-0.1.0.dist-info/RECORD
